README.md
setup.py
ApReusable/ExtendedEnum.py
ApReusable/__init__.py
ApReusable/functions.py
ApReusable/logger.py
ApReusable/renderer.py
ApReusable/validators.py
ApReusable.egg-info/PKG-INFO
ApReusable.egg-info/SOURCES.txt
ApReusable.egg-info/dependency_links.txt
ApReusable.egg-info/requires.txt
ApReusable.egg-info/top_level.txt